webkassa/__init__.py
webkassa/admin.py
webkassa/apps.py
webkassa/forms.py
webkassa/migrations/0001_initial.py
webkassa/migrations/0002_check_order_number.py
webkassa/migrations/0003_remove_webkassaaccount_is_encrypted_and_more.py
webkassa/migrations/0004_alter_webkassaaccount_email_and_more.py
webkassa/migrations/__init__.py
webkassa/models.py
webkassa/serializers.py
webkassa/services/__init__.py
webkassa/services/cron.py
webkassa/services/manager.py
webkassa/services/password_encryption.py
webkassa/settings.py
webkassa/templates/change_password_template.html
elefanto_webkassa-0.4.5.dist-info/METADATA
elefanto_webkassa-0.4.5.dist-info/WHEEL
elefanto_webkassa-0.4.5.dist-info/RECORD
